sinchsms.py
sinchsms-1.0.6.dist-info/LICENSE
sinchsms-1.0.6.dist-info/METADATA
sinchsms-1.0.6.dist-info/WHEEL
sinchsms-1.0.6.dist-info/top_level.txt
sinchsms-1.0.6.dist-info/RECORD
