Metadata-Version: 2.1
Name: sinchsms
Version: 1.0.6
Summary: A module to send sms using the Sinch REST apis, www.sinch.com
Home-page: https://github.com/sinch/python-sinch-sms.git
Author: Slava Savitskiy
Author-email: slava@sinch.com
Keywords: sms,sinch
Classifier: Programming Language :: Python
Classifier: Programming Language :: Python :: 3
Classifier: Intended Audience :: Developers
Classifier: License :: OSI Approved :: Apache Software License
Classifier: Operating System :: OS Independent
Classifier: Topic :: Software Development :: Libraries :: Python Modules
Classifier: Topic :: Communications
Classifier: Development Status :: 4 - Beta
License-File: LICENSE
